{
  "title": "Java",
  "salary":  "20-40K",
  "tags": ["杭州","3-5年","本科"],
  "date": "2020-10-26",
  "labels": ["Java", "中间件", "后端开发"],
  "user": {
    "id": 1,
    "avatar": "./imgs/avatar_14.png",
    "name": "李先生",
    "title": "蚂蚁金服 · 技术专家"
  },
  "body": "1、 理解商户业务，识别需求，用数据赋能商业经营。<br>2、 参与系统架构设计和优化，独立完成系统分析文档的撰写；<br>3、 沉淀有价值的商户数据资产，以数据化的方式联通商户、平台与消费者，打造一站式商户服务体系。<br>4、 有主人公意识和数据感觉，熟悉hadoop，hbase，spark等大数据解决方案。",
  "company": {
    "name": "蚂蚁金服",
    "full_name":"蚂蚁金服（杭州）网络技术有限公司",
    "tags": ["互联网金融", "D轮及以上", "10000人以上"],
    "logo": "./imgs/mayi.jpg",
    "body": "蚂蚁金融服务集团（以下称“蚂蚁金服”）起步于2004年成立的支付宝。2014年10月，蚂蚁金服正式成立。蚂蚁金服以“让信用等于财富”为愿景，致力于打造开放的生态系统，通过“互联网推进器计划”助力金融机构和合作伙伴加速迈向“互联网+”，为小微企业和个人消费者提供普惠金融服务。 蚂蚁金服旗下有支付宝、余额宝、招财宝、蚂蚁聚宝、网商银行、蚂蚁花呗、芝麻信用、蚂蚁金融云、蚂蚁达客等子业务板块。",
    "props": {
      "法人代表": "程立",
      "注册资本": "1000万元人民币",
      "成立时间": "2013-10-22",
      "经营状态": "存续"
    }
  },
  "jobs": [
  {
    "company": "蚂蚁金服",
    "title": "Java",
    "salary":  "20-40K",
    "date": "2020-10-26T06:03:58.439Z",
    "logo": "./imgs/mayi.jpg"       
  },
  {
  "company": "蚂蚁金服",
  "title": "Java",
  "salary":  "20-40K",
  "logo": "./imgs/mayi.jpg",
  "date": "2020-10-26T06:03:58.439Z"
  }
  ],
  "cities": [
    {"id":1, "name": "博尔塔拉"},
    {"id":2, "name": "赤峰"},
    {"id":3, "name": "青岛"},
    {"id":4, "name": "葫芦岛"},
    {"id":5, "name": "乐山"},
    {"id":6, "name": "信阳"},
    {"id":7, "name": "泰州"}
  ],
  "pathes": [
    {"title": "首页", "url": "/"},
    {"title": "杭州招聘·Java招聘", "url": "/"},
    {"title": "杭州Java招聘", "url": "/"},
    {"title": "蚂蚁金服Java招聘", "url": "/"}
  ]
}